bhashan2pathtak/__init__.py
bhashan2pathtak/speech_to_text.py
bhashan2pathtak-0.1.0.dist-info/LICENSE
bhashan2pathtak-0.1.0.dist-info/METADATA
bhashan2pathtak-0.1.0.dist-info/WHEEL
bhashan2pathtak-0.1.0.dist-info/entry_points.txt
bhashan2pathtak-0.1.0.dist-info/top_level.txt
bhashan2pathtak-0.1.0.dist-info/RECORD
