Metadata-Version: 2.1
Name: bhashan2pathtak
Version: 0.1.0
Summary: A simple speech-to-text application using Wit.ai
Home-page: https://github.com/nilukush/bhashan2pathtak
Author: Nilesh Kumar
Author-email: nilukush@gmail.com
Classifier: Development Status :: 3 - Alpha
Classifier: Intended Audience :: Developers
Classifier: License :: OSI Approved :: MIT License
Classifier: Operating System :: OS Independent
Classifier: Programming Language :: Python :: 3
Classifier: Programming Language :: Python :: 3.7
Classifier: Programming Language :: Python :: 3.8
Classifier: Programming Language :: Python :: 3.9
Classifier: Programming Language :: Python :: 3.10
Requires-Python: >=3.7
License-File: LICENSE
Requires-Dist: SpeechRecognition>=3.8.1
Requires-Dist: PyAudio>=0.2.11
Requires-Dist: wit>=6.0.0
